torrentix/__init__.py
torrentix/bencode.py
torrentix/peer.py
torrentix/peer_manager.py
torrentix/torrent.py
torrentix/tracker.py
torrentix-0.2.0.dist-info/licenses/LICENSE
torrentix-0.2.0.dist-info/METADATA
torrentix-0.2.0.dist-info/WHEEL
torrentix-0.2.0.dist-info/top_level.txt
torrentix-0.2.0.dist-info/RECORD
